{
  "tags": [
    {
      "name": "release",
      "version": "1.55.1",
      "commit": "1ef0c81",
      "upstream": "Releases",
      "lastUpdated": "2021-06-16T00:50:46.808Z"
    },
    {
      "name": "testing",
      "version": "1.56.0-beta.5551.80bccacd8",
      "commit": "a1e22f2",
      "upstream": "Beta",
      "lastUpdated": "2021-06-16T00:51:43.734Z"
    },
    {
      "name": "nightly",
      "version": "",
      "commit": "",
      "upstream": "",
      "lastUpdated": ""
    }
  ],
  "pulls": 108446,
  "stars": 5
}
