{
  "tags": [
    {
      "name": "release",
      "version": "1.54.1",
      "commit": "9cedc62",
      "upstream": "Releases",
      "lastUpdated": "2021-03-08T11:34:27.205Z"
    },
    {
      "name": "testing",
      "version": "1.55.0-beta.5337.b8c1cf745",
      "commit": "1669b90",
      "upstream": "Beta",
      "lastUpdated": "2021-03-24T10:18:26.833Z"
    },
    {
      "name": "nightly",
      "version": "",
      "commit": "",
      "upstream": "",
      "lastUpdated": ""
    }
  ],
  "pulls": 101457,
  "stars": 5
}
